main.py
salome2py-0.6.0.dist-info/licenses/LICENSE
salome2py-0.6.0.dist-info/METADATA
salome2py-0.6.0.dist-info/WHEEL
salome2py-0.6.0.dist-info/entry_points.txt
salome2py-0.6.0.dist-info/top_level.txt
salome2py-0.6.0.dist-info/RECORD
